Metadata-Version: 2.1
Name: mercarius
Version: 1.0.0
Summary: mercari-us api-like wrapper
Home-page: https://github.com/marvinody/mercari-us/
Author: marvinody
Author-email: manny@pypi.sadpanda.moe
License: UNKNOWN
Platform: UNKNOWN
Classifier: Programming Language :: Python :: 3.9
